dicekey/__init__.py
dicekey/diceware.py
dicekey-0.0.1.dist-info/LICENSE
dicekey-0.0.1.dist-info/METADATA
dicekey-0.0.1.dist-info/WHEEL
dicekey-0.0.1.dist-info/entry_points.txt
dicekey-0.0.1.dist-info/top_level.txt
dicekey-0.0.1.dist-info/RECORD
