Metadata-Version: 2.1
Name: dicekey
Version: 0.0.1
Summary: A simple Python passphrase generator
Home-page: https://git.krislamo.org/kris/dicekey
Author: Kris Lamoureux
Author-email: Kris Lamoureux <kris@lamoureux.io>
License: GNU GPLv3
Project-URL: Homepage, https://git.krislamo.org/kris/dicekey
Classifier: Programming Language :: Python :: 3
Classifier: License :: OSI Approved :: GNU General Public License v3 (GPLv3)
Classifier: Operating System :: OS Independent
Requires-Python: >=3.7
License-File: LICENSE
